consensusclustering/__init__.py
consensusclustering/consensus.py
consensusclustering-0.2.4.dist-info/LICENSE
consensusclustering-0.2.4.dist-info/METADATA
consensusclustering-0.2.4.dist-info/WHEEL
consensusclustering-0.2.4.dist-info/RECORD
