Metadata-Version: 2.3
Name: consensusclustering
Version: 0.2.4
Summary: Python implementation of Consensus Clustering by Monti et al. (2003)
License: MIT
Author: Ross Burton
Author-email: burtonrossj@gmail.com
Requires-Python: >=3.11
Classifier: License :: OSI Approved :: MIT License
Classifier: Programming Language :: Python :: 3
Classifier: Programming Language :: Python :: 3.11
Classifier: Programming Language :: Python :: 3.12
Classifier: Programming Language :: Python :: 3.13
Requires-Dist: kneed (>=0.8.5)
Requires-Dist: matplotlib (>=3.8.0,<4)
Requires-Dist: numpy (>=2.0.0)
Requires-Dist: pandas (>=2.0.0)
Requires-Dist: seaborn (>=0.13.0)
Requires-Dist: tqdm (>=4.66.1)
